_pygeoapi_process/xsatendpts.py
_pygeoapi_process/xsatpathpts.py
_pygeoapi_process/xsatpoint.py
nldi_xstool/ExtADCPBathy.py
nldi_xstool/PathGen.py
nldi_xstool/XSGen.py
nldi_xstool/__init__.py
nldi_xstool/__main__.py
nldi_xstool/__openChannel.py
nldi_xstool/__openChannel_numba.py
nldi_xstool/ancillary.py
nldi_xstool/centerline.py
nldi_xstool/nldi_xstool.py
nldi_xstool/py.typed
nldi_xstool/tspline.py
nldi_xstool-0.12.17.dist-info/LICENSE.md
nldi_xstool-0.12.17.dist-info/METADATA
nldi_xstool-0.12.17.dist-info/WHEEL
nldi_xstool-0.12.17.dist-info/entry_points.txt
nldi_xstool-0.12.17.dist-info/RECORD
