Metadata-Version: 2.3
Name: nldi-xstool
Version: 0.12.17
Summary: Nldi Xstool
License: LICENSE.md
Author: Richard McDonald
Author-email: rmcd@usgs.gov
Requires-Python: >=3.9,<3.13
Classifier: Development Status :: 1 - Planning
Classifier: License :: Other/Proprietary License
Classifier: Programming Language :: Python :: 3
Classifier: Programming Language :: Python :: 3.9
Classifier: Programming Language :: Python :: 3.10
Classifier: Programming Language :: Python :: 3.11
Classifier: Programming Language :: Python :: 3.12
Classifier: Programming Language :: Python :: 3.8
Requires-Dist: Bottleneck (>=1.3.4)
Requires-Dist: Shapely (>=2,<3)
Requires-Dist: click (>=8.0,<9.0)
Requires-Dist: dask (>=2024.5.1)
Requires-Dist: geopandas (>=0.11.0)
Requires-Dist: netCDF4 (>=1.5.8)
Requires-Dist: numba (>=0.55.1)
Requires-Dist: numpy (>=2,<3)
Requires-Dist: py3dep (>=0.19.0,<0.20.0)
Requires-Dist: pygeoapi (>=0.11.0)
Requires-Dist: pygeohydro (>=0.19.0,<0.20.0)
Requires-Dist: pynhd (>=0.19.0,<0.20.0)
Requires-Dist: xarray (>=2022.3.0)
Project-URL: Changelog, https://code.usgs.gov/wma/nhgf/toolsteam/nldi-xstool/-/releases
Project-URL: Documentation, https://nldi-xstool.readthedocs.io
Project-URL: Homepage, https://code.usgs.gov/wma/nhgf/toolsteam/nldi-xstool
Project-URL: Repository, https://code.usgs.gov/wma/nhgf/toolsteam/nldi-xstool
